model_predictive_control/__init__.py
model_predictive_control/__main__.py
model_predictive_control/base.py
model_predictive_control/cli_bicycle.py
model_predictive_control/cli_drone.py
model_predictive_control/mpc.py
model_predictive_control/trajectory_utils.py
model_predictive_control/cost/__init__.py
model_predictive_control/cost/base.py
model_predictive_control/cost/quadcopter_trajectory_penalty.py
model_predictive_control/cost/test_quadcopter_trajectory_penalty.py
model_predictive_control/cost/trajectory2d_steering_penalty.py
model_predictive_control/models/__init__.py
model_predictive_control/models/base.py
model_predictive_control/models/bicycle.py
model_predictive_control/models/quadcopter.py
model_predictive_control-0.4.0.dist-info/LICENSE
model_predictive_control-0.4.0.dist-info/METADATA
model_predictive_control-0.4.0.dist-info/WHEEL
model_predictive_control-0.4.0.dist-info/entry_points.txt
model_predictive_control-0.4.0.dist-info/top_level.txt
model_predictive_control-0.4.0.dist-info/RECORD
