Metadata-Version: 2.1
Name: model_predictive_control
Version: 0.4.0
Summary: Awesome model_predictive_control created by AdityaNG
Home-page: https://github.com/AdityaNG/model_predictive_control/
Author: AdityaNG
License-File: LICENSE
Requires-Dist: numpy
Requires-Dist: scipy
Requires-Dist: simple-pid
Requires-Dist: pydantic
Requires-Dist: matplotlib
Provides-Extra: test
Requires-Dist: pytest; extra == "test"
Requires-Dist: coverage; extra == "test"
Requires-Dist: flake8; extra == "test"
Requires-Dist: black; extra == "test"
Requires-Dist: isort; extra == "test"
Requires-Dist: pytest-cov; extra == "test"
Requires-Dist: mypy; extra == "test"
Requires-Dist: gitchangelog; extra == "test"
Requires-Dist: mkdocs; extra == "test"
Requires-Dist: lark; extra == "test"
Requires-Dist: types-PyYAML; extra == "test"
Requires-Dist: pytest-mock; extra == "test"
